LICENSE
README.md
setup.py
cgroupspy/__init__.py
cgroupspy/contenttypes.py
cgroupspy/controllers.py
cgroupspy/interfaces.py
cgroupspy/nodes.py
cgroupspy/trees.py
cgroupspy/utils.py
cgroupspy.egg-info/PKG-INFO
cgroupspy.egg-info/SOURCES.txt
cgroupspy.egg-info/dependency_links.txt
cgroupspy.egg-info/top_level.txt