Metadata-Version: 2.1
Name: cgroupspy
Version: 0.2.2
Summary: Python library for managing cgroups
Home-page: https://github.com/cloudsigma/cgroupspy
Author: CloudSigma AG
Author-email: dev-support@cloudsigma.com
Maintainer: Miguel Trujillo
Maintainer-email: miguel@cloudsigma.com
License: New BSD
Keywords: cgroups
Platform: UNKNOWN
Classifier: Programming Language :: Python :: 2.7
Classifier: Programming Language :: Python :: 3
Classifier: Programming Language :: Python :: 3.6
Classifier: Programming Language :: Python :: 3.7
Classifier: Programming Language :: Python :: 3.8
Classifier: Programming Language :: Python :: 3.9
Classifier: Programming Language :: Python :: 3.10
Classifier: Development Status :: 4 - Beta
Classifier: Intended Audience :: System Administrators
Classifier: Intended Audience :: Developers
Classifier: License :: OSI Approved :: BSD License
Requires-Python: >=2.7, !=3.0.*, !=3.1.*, !=3.2.*, !=3.3.*, !=3.4.*, !=3.5.*
License-File: LICENSE
